{
  "basic_info": {
    "description_header": "Hi",
    "description": "I'm a dedicated professional UI/UX designer and full-stack web developer with expertise in MERN programming. I'm Goal-oriented and individually motivated. I work well on teams and I naturally take initiative in order to create and provide potential employers and clients with web applications that meet optimal functionality and expertly polished design. I consistently invest time and energy into expanding programming skills and maintains level of curiosity and precision.  ",
    "section_name": {
      "about": "About me",
      "projects": "Projects",
      "skills": "Skills"
    }
  },
  "projects": [
    {
      "title": "SkinDex",
      "description": "Will allow users to take quiz that shows them a skincare routine base on their answers. This is my most extensive project, i used a lot of technologies and created the API.",
      "images": [
        {
        "images":"images/skindex.jpg"}
      ],
      "url": "http://skindex.herokuapp.com/",
      "technologies": [
        {
          "class": "devicon-sequelize-plain",
          "name": "sequelize"
        },
        {
          "class": "devicon-nodejs-plain",
          "name": "node.js"
        },
        {
          "class": "devicon-react-original",
          "name": "react"
        },
        {
          "class": "devicon-bootstrap-plain",
          "name": "Bootstrap"
        },
        {
          "class": "devicon-javascript-plain",
          "name": "JavaScript"
        },
        {
          "class": "devicon-express-original",
          "name": "Express"
        }
      ],
      "link": "https://github.com/Mariafcc/skindex"
    },
    {
      "title": "FitUp",
      "description": "FitUp can be used to design your next workout.User is given a choice of indoor or outdoor workout and given options to add workouts and save them.",
      "images": [
        {
        "images":"../images/fitUp.jpg"}
      ],
      "url": "http://project-two-2020.herokuapp.com",
      "link": "https://github.com/Mariafcc/FitUp-1",
      "technologies": [
        {
          "class": "devicon-javascript-plain",
          "name": "JavaScript"
        },
        {
          "class": "devicon-handlebars-plain",
          "name": "Handle-Bars"
        },
        {
          "class": "devicon-nodejs-plain",
          "name": "Node.js"
        },
        {
          "class": "devicon-css3-plain",
          "name": "css"
        },
        {
          "class": "devicon-react-original",
          "name": "react"
        },
        {
          "class": "devicon-express-original",
          "name": "Express"
        }
      ]
    },
    {
      "title": "UX/UI Beach Vacation",
      "description": "This design is meant for users that are interested in taking beach vacation but do not know where to go. With a study i have found that users mainly go to vacations based on family or friends recommendation. If a booking site adds a feature like this it will increase the time spent on site as well as the amount of items booked with the site.",
      "images": [
        {
          "images":"../images/uxui.jpg"}
        
      ],
      "url": "https://mariafcc.github.io/sprint19/",
      "link":"https://github.com/Mariafcc/sprint19",
      "technologies": [
        {
          "class": "devicon-figma-plain",
          "name": "Figma"
        }
      ]
    }

  ],
  "experience": [
    {
      "company": "DefOpenSource",
      "title": "Front-End Developer",
      "years": "10.2019 - present",
      "mainTech": [
        "Angular 8/9/10"
      ],
      "technologies": [
        "REST API",
        "RxJS",
        "JavaScript",
        "Bootstrap",
        "MDBootstrap",
        "EF Core",
        ".NET Core",
        "SignalR",
        "Angular Material"
      ]
    },
    {
      "company": "Serros Solutions",
      "title": "Intern",
      "years": "01.2018 - 09.2019",
      "mainTech": [
        "Angular 7/8"
      ],
      "technologies": [
        "RxJS",
        "Django",
        "PHP",
        "JavaScript",
        "DHTMLX Gantt"
      ]
    }
  ]
}